{
    "article_id": "55b39bf3ec3c68abaec7105e4f9f45e0.1590265744.047126",
    "title": "Anla\u015fmal\u0131 bo\u015fanma davas\u0131 nas\u0131l a\u00e7\u0131l\u0131r? Bo\u015fanma protokol\u00fc nas\u0131l haz\u0131rlan\u0131r?",
    "authors": [],
    "canonical_link": "https://www.cnnturk.com/video/hazir-cevap/hukuk/anlasmali-bosanma-davasi-nasil-acilir-bosanma-protokolu-nasil-hazirlanir",
    "url": "http://cnnturk.com/video/hazir-cevap/hukuk/anlasmali-bosanma-davasi-nasil-acilir-bosanma-protokolu-nasil-hazirlanir",
    "top_img": "https://i2.cnnturk.com/i/cnnturk/75/0x0/5e3d3f6317aca90a30db5591.jpg",
    "meta_img": "https://i2.cnnturk.com/i/cnnturk/75/0x0/5e3d3f6317aca90a30db5591.jpg",
    "movies": [],
    "text": "Anla\u015fmal\u0131 bo\u015fanma davas\u0131n\u0131n nas\u0131l a\u00e7\u0131laca\u011f\u0131 ve bo\u015fanma protokol\u00fcn\u00fcn haz\u0131rlanmas\u0131 ile ilgili CNN T\u00dcRK\u2019e konu\u015fan Avukat Ayet Mete Meteo\u011flu s\u00fcreci \u015fu s\u00f6zlerle aktarad\u0131r:\n\n\"Anla\u015fmal\u0131 bo\u015fanma davas\u0131 a\u00e7\u0131labilmesi i\u00e7in taraflar\u0131n evliliklerinin \u00fczerinden bir y\u0131l ge\u00e7mi\u015f olmas\u0131 gerekir. Aksi halde anla\u015fmal\u0131 bo\u015fanma davas\u0131 a\u00e7amazlar. Yine anla\u015fmal\u0131 bo\u015fanma davas\u0131 a\u00e7\u0131labilmesi i\u00e7in taraflar\u0131n bo\u015fanma ve bo\u015fanman\u0131n hukuki sonu\u00e7lar\u0131 \u00fczerinde fikir birli\u011fine varm\u0131\u015f olmalar\u0131 ve bunu bir protokole d\u00f6km\u00fc\u015f olmalar\u0131 gerekir. Protokol derken; taraflar\u0131n m\u00fc\u015fterek \u00e7ocuklar\u0131 varsa, m\u00fc\u015fterek \u00e7ocuklar\u0131n velayeti; taraflar\u0131n birbirinden nafaka talebi varsa nafaka talepleri ve miktarlar\u0131; yine tazminat ve mal payla\u015f\u0131m\u0131 talepleri varsa, t\u00fcm bu taleplerin yer ald\u0131\u011f\u0131 bir protokol haz\u0131rlan\u0131r, e\u015fler taraf\u0131ndan imzalan\u0131p bulunduklar\u0131 yerdeki aile mahkemesine dilek\u00e7eyle birlikte verilerek dava a\u00e7\u0131labilir. Yine anla\u015fmal\u0131 bo\u015fanman\u0131n olmas\u0131 i\u00e7in hakimin bu anla\u015fmay\u0131 kabul etmesi gerekir. Aksi halde anla\u015fmal\u0131 bo\u015fanma olmayacakt\u0131r.\"",
    "keywords": [
        "varsa",
        "a\u00e7\u0131l\u0131r",
        "protokol\u00fc",
        "haz\u0131rlan\u0131r",
        "anla\u015fmal\u0131",
        "i\u00e7in",
        "bo\u015fanma",
        "ve",
        "yine",
        "gerekir",
        "bir",
        "nas\u0131l",
        "taraflar\u0131n",
        "davas\u0131"
    ],
    "meta_keywords": [
        "avukat",
        "anla\u015fmal\u0131 bo\u015fanma",
        "bo\u015fanma",
        "Ayet Mete Meteo\u011flu"
    ],
    "publish_date": null,
    "summary": "Anla\u015fmal\u0131 bo\u015fanma davas\u0131n\u0131n nas\u0131l a\u00e7\u0131laca\u011f\u0131 ve bo\u015fanma protokol\u00fcn\u00fcn haz\u0131rlanmas\u0131 ile ilgili CNN T\u00dcRK\u2019e konu\u015fan Avukat Ayet Mete Meteo\u011flu s\u00fcreci \u015fu s\u00f6zlerle aktarad\u0131r:\"Anla\u015fmal\u0131 bo\u015fanma davas\u0131 a\u00e7\u0131labilmesi i\u00e7in taraflar\u0131n evliliklerinin \u00fczerinden bir y\u0131l ge\u00e7mi\u015f olmas\u0131 gerekir.\nAksi halde anla\u015fmal\u0131 bo\u015fanma davas\u0131 a\u00e7amazlar.\nYine anla\u015fmal\u0131 bo\u015fanma davas\u0131 a\u00e7\u0131labilmesi i\u00e7in taraflar\u0131n bo\u015fanma ve bo\u015fanman\u0131n hukuki sonu\u00e7lar\u0131 \u00fczerinde fikir birli\u011fine varm\u0131\u015f olmalar\u0131 ve bunu bir protokole d\u00f6km\u00fc\u015f olmalar\u0131 gerekir.\nProtokol derken; taraflar\u0131n m\u00fc\u015fterek \u00e7ocuklar\u0131 varsa, m\u00fc\u015fterek \u00e7ocuklar\u0131n velayeti; taraflar\u0131n birbirinden nafaka talebi varsa nafaka talepleri ve miktarlar\u0131; yine tazminat ve mal payla\u015f\u0131m\u0131 talepleri varsa, t\u00fcm bu taleplerin yer ald\u0131\u011f\u0131 bir protokol haz\u0131rlan\u0131r, e\u015fler taraf\u0131ndan imzalan\u0131p bulunduklar\u0131 yerdeki aile mahkemesine dilek\u00e7eyle birlikte verilerek dava a\u00e7\u0131labilir.\nYine anla\u015fmal\u0131 bo\u015fanman\u0131n olmas\u0131 i\u00e7in hakimin bu anla\u015fmay\u0131 kabul etmesi gerekir.\nAksi halde anla\u015fmal\u0131 bo\u015fanma olmayacakt\u0131r.\"",
    "article_html": "",
    "meta_description": "Mevcut hukuk sistemimizde, e\u015fleriyle anla\u015fmal\u0131 olarak yollar\u0131n\u0131 ay\u0131rmak ve bo\u015fanmak isteyenler genellikle anla\u015fmal\u0131 bo\u015fanma yolunu tercih ediyorlar. Peki, anla\u015fmal\u0131 bo\u015fanma davas\u0131 nas\u0131l a\u00e7\u0131l\u0131r? Anla\u015fmal\u0131 bo\u015fanma i\u00e7in gerekli olan \u201cBo\u015fanma protokol\u00fc nas\u0131l haz\u0131rlan\u0131r? Anla\u015fmal\u0131 bo\u015fanma davas\u0131n\u0131n a\u00e7\u0131lmas\u0131 ve bo\u015fanma...",
    "meta_lang": "tr"
}