{
    "article_id": "07109ce1100fb76ac5b2ba1bccf81c90.1590265729.662452",
    "title": "Hansel ve Gretel Masal\u0131 Oku - Bir oduncu ve 2 \u00e7ocu\u011fu\u2026",
    "authors": [],
    "canonical_link": "https://www.milliyet.com.tr/cocuk/kultur-sanat/hansel-ve-gretel-masali-oku-bir-oduncu-ve-2-cocugu-6197801",
    "url": "http://milliyet.com.tr/cocuk/kultur-sanat/hansel-ve-gretel-masali-oku-bir-oduncu-ve-2-cocugu-6197801",
    "top_img": "https://i2.milimaj.com/i/milliyet/75/0x0/5ea2dac8adcdeb01d41be4e4.jpg",
    "meta_img": "https://i2.milimaj.com/i/milliyet/75/0x0/5ea2dac8adcdeb01d41be4e4.jpg",
    "movies": [],
    "text": "Gel zaman, git zaman\u2026 Masal oku her zaman\u2026\n\nZaman\u0131n birinde, orman\u0131n giri\u015finde bir oduncu ve iki \u00e7ocu\u011fu ya\u015farm\u0131\u015f. Bu \u00e7ocuklar\u0131n ad\u0131 Hansel ve Gretel\u2019mi\u015f. \u0130ki k\u00fc\u00e7\u00fck \u00e7ocu\u011fun anneleri, onlar bebekken \u00f6lm\u00fc\u015f. Babalar\u0131 tekrar evlenmi\u015f ama yeni anneleri onlardan pek ho\u015flanm\u0131yormu\u015f.\n\nHer ak\u015fam babas\u0131na bu \u00e7ocuklar bize y\u00fck oluyor, onlar\u0131 buradan g\u00f6ndermemiz laz\u0131m diye bask\u0131 yap\u0131yormu\u015f. Bir g\u00fcn bir plan yapm\u0131\u015f ve kocas\u0131na da anlatm\u0131\u015f. Plan\u0131n\u0131 anlat\u0131rken Hansel hepsini duymu\u015f. \u00dcvey anne onlar\u0131 ormana g\u00f6t\u00fcr\u00fcp orada b\u0131rakmay\u0131 planlad\u0131\u011f\u0131 i\u00e7in Hansel bah\u00e7eden \u00e7ak\u0131l ta\u015flar\u0131 toplay\u0131p cebine koymu\u015f.\n\nErtesi g\u00fcn babalar\u0131 ve anneleri onlar\u0131 orman\u0131n derinliklerine kadar g\u00f6t\u00fcr\u00fcp, geri geleceklerini s\u00f6ylemi\u015fler. Planlar\u0131 onlar\u0131 orada b\u0131rak\u0131p onlardan kurtulmakm\u0131\u015f ama bir \u015feyi fark etmemi\u015fler. Hansel yol boyunca cebine doldurdu\u011fu \u00e7ak\u0131l ta\u015flar\u0131n\u0131 yola dizmi\u015f. O ta\u015flar\u0131 izleyerek eve geri d\u00f6nm\u00fc\u015fler.\n\nBabalar\u0131 onlar\u0131 g\u00f6r\u00fcnce \u00e7ok sevinmi\u015f \u00e7\u00fcnk\u00fc onlar\u0131 orada b\u0131rakt\u0131\u011f\u0131 i\u00e7in \u00e7ok \u00fczg\u00fcnm\u00fc\u015f. \u00dcvey anneleri ise bu duruma hi\u00e7 sevinmemi\u015f.\n\n\u00dcvey anneleri bu sefer gece uyurlarken kap\u0131lar\u0131n\u0131 kilitlemi\u015f. Hansel \u00e7ak\u0131l ta\u015f\u0131 toplayamam\u0131\u015f. Sabah evden \u00e7\u0131karken babas\u0131n\u0131n ona verdi\u011fi ekme\u011fi yememi\u015f ve yol boyunca k\u0131r\u0131nt\u0131lar\u0131 yere b\u0131rakm\u0131\u015f. Bir \u015feyi fark edememi\u015f ama\u2026 K\u0131r\u0131nt\u0131lar\u0131 ku\u015flar yemi\u015f ve geri d\u00f6n\u00fc\u015f yolu yok olmu\u015f.\n\nAnne ve babalar\u0131 geri gelece\u011fiz deyip yine yok olmu\u015flar. Hansel ve Gretel ormanda birka\u00e7 g\u00fcn a\u00e7 gezmi\u015fler. Tam yemek bulmaktan umudu kestiklerinde kar\u015f\u0131lar\u0131na \u00e7ikolata ve kurabiyeden yap\u0131lm\u0131\u015f bir ev \u00e7\u0131km\u0131\u015f. Hemen evden birer par\u00e7a yemi\u015fler.\n\nO s\u0131rada evin i\u00e7inden ya\u015fl\u0131 bir kad\u0131n \u00e7\u0131km\u0131\u015f. Onlar\u0131 i\u00e7eri \u00e7a\u011f\u0131r\u0131p onlara bir s\u00fcr\u00fc yemek vermi\u015f. Evin i\u00e7i d\u0131\u015f\u0131 gibi s\u00fcsl\u00fc de\u011fil aksine \u00e7ok korkun\u00e7mu\u015f. Demir kap\u0131n\u0131n arkas\u0131nda ise bir s\u00fcr\u00fc alt\u0131n varm\u0131\u015f.\n\nYa\u015fl\u0131 kad\u0131n asl\u0131nda bir cad\u0131ym\u0131\u015f ve plan\u0131 bu iki \u00e7ocu\u011fu besleyip yemekmi\u015f. Hansel'in alt\u0131nlar\u0131 g\u00f6rd\u00fc\u011f\u00fcn\u00fc g\u00f6r\u00fcnce de onu bir kafese kapatm\u0131\u015f. Gretel\u2019e de zorla yemek pi\u015firtip Hansel\u2019e vermesini s\u00f6ylemi\u015f.\n\nHansel ona verilen yemekleri kafesin yan taraf\u0131na d\u00f6k\u00fcyormu\u015f ve b\u00f6ylece kilo alm\u0131yormu\u015f. Birka\u00e7 g\u00fcn sonra olan biteni fark eden cad\u0131, Hansel\u2019i zay\u0131f haliyle yeme\u011fe karar vermi\u015f ve Gretel\u2019e f\u0131r\u0131n\u0131 yakmas\u0131n\u0131 s\u00f6ylemi\u015f.\n\nGretel f\u0131r\u0131n\u0131 yakm\u0131\u015f ama bir plan\u0131 varm\u0131\u015f. Cad\u0131y\u0131 \u00e7a\u011f\u0131r\u0131p f\u0131r\u0131n\u0131n \u0131s\u0131nmad\u0131\u011f\u0131n\u0131 s\u00f6ylemi\u015f. Cad\u0131 f\u0131r\u0131na do\u011fru e\u011filince de onu iterek f\u0131r\u0131n\u0131n kapa\u011f\u0131n\u0131 kapatm\u0131\u015f. Cad\u0131dan kurtulunca Hansel\u2019i kafesten \u00e7\u0131karm\u0131\u015f.\n\nHansel ve Gretel, cad\u0131n\u0131n alt\u0131nlar\u0131n\u0131 da alarak evden ka\u00e7m\u0131\u015flar. O kadar h\u0131zl\u0131 ko\u015fmu\u015flar ki fark etmeden evlerine varm\u0131\u015flar. Eve vard\u0131klar\u0131nda babalar\u0131n\u0131 kap\u0131n\u0131n \u00f6n\u00fcnde a\u011flarken bulmu\u015flar.\n\nBabalar\u0131 onlar\u0131 g\u00f6r\u00fcnce \u00e7ok sevinmi\u015f ve \u00fcvey annelerinin gitti\u011fini s\u00f6ylemi\u015f. Hansel ve Gretel olanlar\u0131 anlat\u0131p alt\u0131nlar\u0131 babalar\u0131na vermi\u015fler.\n\nArt\u0131k fakir olmayan ormanc\u0131 ve \u00e7ocuklar \u00e7ok mutlu ve ne\u015feli hayat ya\u015fam\u0131\u015flar.",
    "keywords": [
        "\u00e7ok",
        "bu",
        "fark",
        "masal\u0131",
        "\u00e7ocu\u011fu",
        "hansel",
        "g\u00fcn",
        "geri",
        "oku",
        "anneleri",
        "oduncu",
        "onlar\u0131",
        "ve",
        "bir",
        "gretel"
    ],
    "meta_keywords": [
        ""
    ],
    "publish_date": null,
    "summary": "Gel zaman, git zaman\u2026 Masal oku her zaman\u2026Zaman\u0131n birinde, orman\u0131n giri\u015finde bir oduncu ve iki \u00e7ocu\u011fu ya\u015farm\u0131\u015f.\nBu \u00e7ocuklar\u0131n ad\u0131 Hansel ve Gretel\u2019mi\u015f.\n\u0130ki k\u00fc\u00e7\u00fck \u00e7ocu\u011fun anneleri, onlar bebekken \u00f6lm\u00fc\u015f.\nBabalar\u0131 tekrar evlenmi\u015f ama yeni anneleri onlardan pek ho\u015flanm\u0131yormu\u015f.\nHer ak\u015fam babas\u0131na bu \u00e7ocuklar bize y\u00fck oluyor, onlar\u0131 buradan g\u00f6ndermemiz laz\u0131m diye bask\u0131 yap\u0131yormu\u015f.\nBir g\u00fcn bir plan yapm\u0131\u015f ve kocas\u0131na da anlatm\u0131\u015f.\nPlan\u0131n\u0131 anlat\u0131rken Hansel hepsini duymu\u015f.\n\u00dcvey anne onlar\u0131 ormana g\u00f6t\u00fcr\u00fcp orada b\u0131rakmay\u0131 planlad\u0131\u011f\u0131 i\u00e7in Hansel bah\u00e7eden \u00e7ak\u0131l ta\u015flar\u0131 toplay\u0131p cebine koymu\u015f.\nErtesi g\u00fcn babalar\u0131 ve anneleri onlar\u0131 orman\u0131n derinliklerine kadar g\u00f6t\u00fcr\u00fcp, geri geleceklerini s\u00f6ylemi\u015fler.\nPlanlar\u0131 onlar\u0131 orada b\u0131rak\u0131p onlardan kurtulmakm\u0131\u015f ama bir \u015feyi fark etmemi\u015fler.\nHansel yol boyunca cebine doldurdu\u011fu \u00e7ak\u0131l ta\u015flar\u0131n\u0131 yola dizmi\u015f.\nO ta\u015flar\u0131 izleyerek eve geri d\u00f6nm\u00fc\u015fler.\nBabalar\u0131 onlar\u0131 g\u00f6r\u00fcnce \u00e7ok sevinmi\u015f \u00e7\u00fcnk\u00fc onlar\u0131 orada b\u0131rakt\u0131\u011f\u0131 i\u00e7in \u00e7ok \u00fczg\u00fcnm\u00fc\u015f.\n\u00dcvey anneleri ise bu duruma hi\u00e7 sevinmemi\u015f.\n\u00dcvey anneleri bu sefer gece uyurlarken kap\u0131lar\u0131n\u0131 kilitlemi\u015f.\nHansel \u00e7ak\u0131l ta\u015f\u0131 toplayamam\u0131\u015f.\nSabah evden \u00e7\u0131karken babas\u0131n\u0131n ona verdi\u011fi ekme\u011fi yememi\u015f ve yol boyunca k\u0131r\u0131nt\u0131lar\u0131 yere b\u0131rakm\u0131\u015f.\nBir \u015feyi fark edememi\u015f ama\u2026 K\u0131r\u0131nt\u0131lar\u0131 ku\u015flar yemi\u015f ve geri d\u00f6n\u00fc\u015f yolu yok olmu\u015f.\nAnne ve babalar\u0131 geri gelece\u011fiz deyip yine yok olmu\u015flar.\nHansel ve Gretel ormanda birka\u00e7 g\u00fcn a\u00e7 gezmi\u015fler.\nTam yemek bulmaktan umudu kestiklerinde kar\u015f\u0131lar\u0131na \u00e7ikolata ve kurabiyeden yap\u0131lm\u0131\u015f bir ev \u00e7\u0131km\u0131\u015f.\nHemen evden birer par\u00e7a yemi\u015fler.\nO s\u0131rada evin i\u00e7inden ya\u015fl\u0131 bir kad\u0131n \u00e7\u0131km\u0131\u015f.\nOnlar\u0131 i\u00e7eri \u00e7a\u011f\u0131r\u0131p onlara bir s\u00fcr\u00fc yemek vermi\u015f.\nEvin i\u00e7i d\u0131\u015f\u0131 gibi s\u00fcsl\u00fc de\u011fil aksine \u00e7ok korkun\u00e7mu\u015f.\nDemir kap\u0131n\u0131n arkas\u0131nda ise bir s\u00fcr\u00fc alt\u0131n varm\u0131\u015f.\nYa\u015fl\u0131 kad\u0131n asl\u0131nda bir cad\u0131ym\u0131\u015f ve plan\u0131 bu iki \u00e7ocu\u011fu besleyip yemekmi\u015f.\nHansel'in alt\u0131nlar\u0131 g\u00f6rd\u00fc\u011f\u00fcn\u00fc g\u00f6r\u00fcnce de onu bir kafese kapatm\u0131\u015f.\nGretel\u2019e de zorla yemek pi\u015firtip Hansel\u2019e vermesini s\u00f6ylemi\u015f.\nHansel ona verilen yemekleri kafesin yan taraf\u0131na d\u00f6k\u00fcyormu\u015f ve b\u00f6ylece kilo alm\u0131yormu\u015f.\nBirka\u00e7 g\u00fcn sonra olan biteni fark eden cad\u0131, Hansel\u2019i zay\u0131f haliyle yeme\u011fe karar vermi\u015f ve Gretel\u2019e f\u0131r\u0131n\u0131 yakmas\u0131n\u0131 s\u00f6ylemi\u015f.\nGretel f\u0131r\u0131n\u0131 yakm\u0131\u015f ama bir plan\u0131 varm\u0131\u015f.\nCad\u0131y\u0131 \u00e7a\u011f\u0131r\u0131p f\u0131r\u0131n\u0131n \u0131s\u0131nmad\u0131\u011f\u0131n\u0131 s\u00f6ylemi\u015f.\nCad\u0131 f\u0131r\u0131na do\u011fru e\u011filince de onu iterek f\u0131r\u0131n\u0131n kapa\u011f\u0131n\u0131 kapatm\u0131\u015f.\nCad\u0131dan kurtulunca Hansel\u2019i kafesten \u00e7\u0131karm\u0131\u015f.\nHansel ve Gretel, cad\u0131n\u0131n alt\u0131nlar\u0131n\u0131 da alarak evden ka\u00e7m\u0131\u015flar.\nO kadar h\u0131zl\u0131 ko\u015fmu\u015flar ki fark etmeden evlerine varm\u0131\u015flar.\nEve vard\u0131klar\u0131nda babalar\u0131n\u0131 kap\u0131n\u0131n \u00f6n\u00fcnde a\u011flarken bulmu\u015flar.\nBabalar\u0131 onlar\u0131 g\u00f6r\u00fcnce \u00e7ok sevinmi\u015f ve \u00fcvey annelerinin gitti\u011fini s\u00f6ylemi\u015f.\nHansel ve Gretel olanlar\u0131 anlat\u0131p alt\u0131nlar\u0131 babalar\u0131na vermi\u015fler.\nArt\u0131k fakir olmayan ormanc\u0131 ve \u00e7ocuklar \u00e7ok mutlu ve ne\u015feli hayat ya\u015fam\u0131\u015flar.",
    "article_html": "",
    "meta_description": ".",
    "meta_lang": "tr"
}